splitiorequests/__init__.py
splitiorequests/api/__init__.py
splitiorequests/api/environments.py
splitiorequests/api/splits.py
splitiorequests/api/tags.py
splitiorequests/api/traffic_types.py
splitiorequests/api/workspaces.py
splitiorequests/common/__init__.py
splitiorequests/common/http_adapter.py
splitiorequests/common/utils.py
splitiorequests/models/__init__.py
splitiorequests/models/environments/__init__.py
splitiorequests/models/environments/environment.py
splitiorequests/models/splits/__init__.py
splitiorequests/models/splits/between.py
splitiorequests/models/splits/bucket.py
splitiorequests/models/splits/condition.py
splitiorequests/models/splits/default_rule.py
splitiorequests/models/splits/depends.py
splitiorequests/models/splits/environment.py
splitiorequests/models/splits/matcher.py
splitiorequests/models/splits/rule.py
splitiorequests/models/splits/split.py
splitiorequests/models/splits/split_definition.py
splitiorequests/models/splits/split_definitions.py
splitiorequests/models/splits/splits.py
splitiorequests/models/splits/tag.py
splitiorequests/models/splits/traffic_type.py
splitiorequests/models/splits/treatment.py
splitiorequests/models/tags/__init__.py
splitiorequests/models/tags/tag.py
splitiorequests/models/tags/tags.py
splitiorequests/models/traffictypes/__init__.py
splitiorequests/models/traffictypes/traffic_type.py
splitiorequests/models/workspaces/__init__.py
splitiorequests/models/workspaces/workspace.py
splitiorequests/models/workspaces/workspaces.py
splitiorequests/schemas/__init__.py
splitiorequests/schemas/environments/__init__.py
splitiorequests/schemas/environments/environment_schema.py
splitiorequests/schemas/environments/environment_schema_exclude.py
splitiorequests/schemas/splits/__init__.py
splitiorequests/schemas/splits/between_schema.py
splitiorequests/schemas/splits/between_schema_exclude.py
splitiorequests/schemas/splits/bucket_schema.py
splitiorequests/schemas/splits/bucket_schema_exclude.py
splitio_requests-1.1.0.dist-info/LICENSE
splitio_requests-1.1.0.dist-info/METADATA
splitio_requests-1.1.0.dist-info/WHEEL
splitio_requests-1.1.0.dist-info/top_level.txt
splitio_requests-1.1.0.dist-info/RECORD
